{
    "nome": "testeJOAOVITOR",
    "url": "jdbc:mysql://localhost/databasejv",
    "porta": 3306,
    "usuario": "root",
    "senha": "",
    "sgbd": 1,
    "tabela": [
        {
            "nomeTabela": "databasejv14",
            "coluna": [
                {
                    "nome": "tabela1zin",
                    "tipo": "varchar(20)",
                    "isNotNull": true,
                    "isAutoIncrement": true,
                    "isPrimaryKey": true
                },
                {
                    "nome": "tabela1",
                    "tipo": "varchar(20)",
                    "isNotNull": false,
                    "isAutoIncrement": false,
                    "isPrimaryKey": false
                }
            ]
        }
    ]
}